moffetthub_cli/__init__.py
moffetthub_cli/main.py
moffetthub_cli/utils.py
moffetthub_cli-0.1.0.dist-info/METADATA
moffetthub_cli-0.1.0.dist-info/WHEEL
moffetthub_cli-0.1.0.dist-info/entry_points.txt
moffetthub_cli-0.1.0.dist-info/top_level.txt
moffetthub_cli-0.1.0.dist-info/RECORD
