Metadata-Version: 2.4
Name: moffetthub-cli
Version: 0.1.0
Summary: A CLI tool for querying and downloading files from MoffettHub.
Home-page: https://github.com/yourusername/moffetthub-cli
Author: orion.zou
Author-email: guangyuan.zou@moffett.ai
Classifier: Programming Language :: Python :: 3
Classifier: License :: OSI Approved :: MIT License
Classifier: Operating System :: OS Independent
Requires-Python: >=3.9
Requires-Dist: requests
Requires-Dist: tqdm
Dynamic: author
Dynamic: author-email
Dynamic: classifier
Dynamic: description
Dynamic: description-content-type
Dynamic: home-page
Dynamic: requires-dist
Dynamic: requires-python
Dynamic: summary
